reshape/__init__.py
reshape/cli.py
reshape-0.2.0.dist-info/DESCRIPTION.rst
reshape-0.2.0.dist-info/METADATA
reshape-0.2.0.dist-info/RECORD
reshape-0.2.0.dist-info/WHEEL
reshape-0.2.0.dist-info/entry_points.txt
reshape-0.2.0.dist-info/metadata.json
reshape-0.2.0.dist-info/top_level.txt
