Metadata-Version: 2.0
Name: reshape
Version: 0.2.0
Summary: The missing reshape for Python
Home-page: https://github.com/hvnsweeting/reshape
Author: Viet Hung Nguyen
Author-email: hvn@familug.org
License: MIT license
Keywords: reshape
Platform: UNKNOWN
Classifier: Development Status :: 2 - Pre-Alpha
Classifier: Intended Audience :: Developers
Classifier: License :: OSI Approved :: MIT License
Classifier: Natural Language :: English
Classifier: Programming Language :: Python :: 2
Classifier: Programming Language :: Python :: 2.7
Classifier: Programming Language :: Python :: 3
Classifier: Programming Language :: Python :: 3.3
Classifier: Programming Language :: Python :: 3.4
Classifier: Programming Language :: Python :: 3.5
Requires-Dist: Click (>=6.0)
